nexus_uploader/__init__.py
nexus_uploader/nexus.py
nexus_uploader/nexus_upload_cmd.py
nexus_uploader/pip_compile.py
nexus_uploader/pypi.py
nexus_uploader/pyrequirements2nexus.py
nexus_uploader/requirements.py
nexus_uploader/utils.py
nexus_uploader-1.0.17.dist-info/DESCRIPTION.rst
nexus_uploader-1.0.17.dist-info/METADATA
nexus_uploader-1.0.17.dist-info/RECORD
nexus_uploader-1.0.17.dist-info/WHEEL
nexus_uploader-1.0.17.dist-info/entry_points.txt
nexus_uploader-1.0.17.dist-info/metadata.json
nexus_uploader-1.0.17.dist-info/top_level.txt
nexus_uploader-1.0.17.dist-info/zip-safe
tests/__init__.py
tests/conftest.py
tests/pytest_markers.py
tests/smoke_test_extract_classifier_and_extension.py
tests/test_extract_classifier_and_extension.py
tests/test_get_package_release_from_pypi.py
tests/test_nexus.py
tests/test_pip_compile.py
tests/test_requirements.py
