Metadata-Version: 2.0
Name: nexus-uploader
Version: 1.0.17
Summary: CLI tool to upload Python packages listed in a requirements.txt file into a Sonatype Nexus (from Pypi), and return the list of the artifact URLs
Home-page: http://github.com/voyages-sncf-technologies/nexus_uploader
Author: Lucas Cimon
Author-email: lucas.cimon+pypi@gmail.com
License: Apache License 2.0
Keywords: nexus artifacts packages upload requirements pip-compile
Platform: UNKNOWN
Classifier: Intended Audience :: Developers
Classifier: Development Status :: 5 - Production/Stable
Classifier: License :: OSI Approved :: Apache Software License
Classifier: Natural Language :: English
Classifier: Programming Language :: Python
Classifier: Programming Language :: Python :: 3
Classifier: Programming Language :: Python :: 2
Classifier: Operating System :: OS Independent
Classifier: Topic :: Utilities
Classifier: Topic :: Software Development :: Libraries :: Python Modules
Classifier: Topic :: System :: Archiving :: Packaging
Requires-Dist: pip (<=9.0.3,>=8.1.1)
Requires-Dist: pip-tools (<=1.11.0,>=1.10.0)
Requires-Dist: requests (>=2.8.1)
